[
  {
    "ApiId": "/providers/microsoft.powerapps/apis/shared_sharepointonline",
    "CdpRevision": {
      "BaseUrl": "/",
      "LastChangedTimeString": "2023-03-27T17:17:13.2870000Z",
      "RevisionNumber": 1
    },
    "ConnectedDataSourceInfoNameMapping": {
      "{Attachments}": "Attachments",
      "{Attachments}@odata.type": "{Attachments} ({Attachments}@odata.type)",
      "{FilenameWithExtension}": "File name with extension",
      "{FullPath}": "Full Path",
      "{HasAttachments}": "Has attachments",
      "{Identifier}": "Identifier",
      "{IsFolder}": "IsFolder",
      "{Link}": "Link to item",
      "{ModerationComment}": "Comments associated with the content approval of this list item",
      "{ModerationStatus}": "Content approval status",
      "{Name}": "Name",
      "{Path}": "Folder path",
      "{Thumbnail}": "Thumbnail",
      "{TriggerWindowEndToken}": "Trigger Window End Token",
      "{TriggerWindowStartToken}": "Trigger Window Start Token",
      "{VersionNumber}": "Version number",
      "Author": "Created By",
      "Author#Claims": "Created By Claims",
      "ComplianceAssetId": "Compliance Asset Id",
      "Created": "Created",
      "Editor": "Modified By",
      "Editor#Claims": "Modified By Claims",
      "ID": "ID",
      "Index_x0020_01": "Index 01",
      "Index_x0020_01#Id": "Index 01 Id",
      "Index_x0020_02": "Index 02",
      "Index_x0020_02#Id": "Index 02 Id",
      "Index_x0020_03": "Index 03",
      "Index_x0020_03#Id": "Index 03 Id",
      "Index_x0020_04": "Index 04",
      "Index_x0020_04#Id": "Index 04 Id",
      "Index_x0020_05": "Index 05",
      "Index_x0020_05#Id": "Index 05 Id",
      "Index_x0020_06": "Index 06",
      "Index_x0020_06#Id": "Index 06 Id",
      "Index_x0020_07": "Index 07",
      "Index_x0020_07#Id": "Index 07 Id",
      "Index_x0020_08": "Index 08",
      "Index_x0020_08#Id": "Index 08 Id",
      "Index_x0020_09": "Index 09",
      "Index_x0020_09#Id": "Index 09 Id",
      "Index_x0020_10": "Index 10",
      "Index_x0020_10#Id": "Index 10 Id",
      "Modified": "Modified",
      "OData__ColorTag": "Color Tag",
      "Title": "Title"
    },
    "DatasetName": "https://massl.sharepoint.com/sites/LineaIntimo/IEDigitalization",
    "EncodeDataset": true,
    "IsSampleData": false,
    "IsWritable": true,
    "Name": "Master Style - Index",
    "Type": "ConnectedDataSourceInfo"
  }
]